LICENSE
MANIFEST.in
README.md
setup.py
qpruvcheig/__init__.py
qpruvcheig/api_helper.py
qpruvcheig/configuration.py
qpruvcheig/decorators.py
qpruvcheig/qpruvcheig_client.py
qpruvcheig.egg-info/PKG-INFO
qpruvcheig.egg-info/SOURCES.txt
qpruvcheig.egg-info/dependency_links.txt
qpruvcheig.egg-info/requires.txt
qpruvcheig.egg-info/top_level.txt
qpruvcheig/controllers/__init__.py
qpruvcheig/controllers/api_controller.py
qpruvcheig/controllers/base_controller.py
qpruvcheig/exceptions/__init__.py
qpruvcheig/exceptions/api_exception.py
qpruvcheig/http/__init__.py
qpruvcheig/http/http_call_back.py
qpruvcheig/http/http_client.py
qpruvcheig/http/http_context.py
qpruvcheig/http/http_method_enum.py
qpruvcheig/http/http_request.py
qpruvcheig/http/http_response.py
qpruvcheig/http/requests_client.py
qpruvcheig/http/auth/__init__.py
qpruvcheig/http/auth/basic_auth.py
qpruvcheig/models/__init__.py
qpruvcheig/models/suite_code_enum.py
tests/__init__.py
tests/http_response_catcher.py
tests/test_helper.py
tests/controllers/__init__.py
tests/controllers/controller_test_base.py
tests/controllers/test_api_controller.py